pipfile/__about__.py
pipfile/__init__.py
pipfile/api.py
pipfile-0.0.1.dist-info/DESCRIPTION.rst
pipfile-0.0.1.dist-info/METADATA
pipfile-0.0.1.dist-info/RECORD
pipfile-0.0.1.dist-info/WHEEL
pipfile-0.0.1.dist-info/metadata.json
pipfile-0.0.1.dist-info/top_level.txt
